{
  "audio" : {
    "name" : "en-us-he.ogg",
    "url" : "http://upload.wikimedia.org/wikipedia/commons/2/2f/En-us-he.ogg",
    "include" : true
  },
  "audio_url" : "http://upload.wikimedia.org/wikipedia/commons/2/2f/En-us-he.ogg",
  "id" : "345682",
  "ipa" : "/ˈhiː/",
  "rank" : 15,
  "synonyms" : [ {
    "text" : "(person whose gender is unknown) he or she, he/she, s/he, they, or these other third-person pronouns",
    "include" : true
  }, {
    "text" : "(animal whose gender is unknown) it",
    "include" : true
  } ],
  "title" : "he",
  "translations" : [ {
    "text" : "il",
    "include" : true
  } ],
  "types" : [ {
    "definitions" : [ {
      "quotations" : [ {
        "text" : "Though Bane’s sing-song voice gives his pronouncements a funny lilt, <em>he</em> doesn’t have any of the Joker’s deranged wit, and Nolan isn’t interested in undercutting his seriousness for the sake of a breezier entertainment.",
        "include" : false,
        "card_sample" : false
      } ],
      "text" : "(personal) A male person or animal already known or implied.",
      "include" : true
    }, {
      "text" : "A person whose gender is unknown or irrelevant.",
      "include" : true
    }, {
      "text" : "(personal) An animal whose gender is unknown.",
      "include" : true
    } ],
    "type" : "Pronoun",
    "include" : true
  }, {
    "definitions" : [ {
      "text" : "(AAVE) (lang=en)",
      "include" : true
    } ],
    "type" : "Determiner",
    "include" : false
  }, {
    "definitions" : [ {
      "text" : "(uncountable) The game of tag, or it, in which the player attempting to catch the others is called \"he\".",
      "include" : false
    }, {
      "quotations" : [ {
        "text" : "Alex totally is a <em>he</em>.",
        "include" : true,
        "card_sample" : false
      } ],
      "text" : "(informal) A male person.",
      "include" : true
    } ],
    "type" : "Noun",
    "include" : true
  } ],
  "copyByValue" : true,
  "card_translate" : false,
  "card_images" : false,
  "images" : [ ]
}